fastimgconcat/README.md
fastimgconcat/__init__.py
fastimgconcat/requirements.txt
fastimgconcat/thirdparty.json
fastimgconcat-0.10.dist-info/LICENSE.rst
fastimgconcat-0.10.dist-info/METADATA
fastimgconcat-0.10.dist-info/WHEEL
fastimgconcat-0.10.dist-info/top_level.txt
fastimgconcat-0.10.dist-info/RECORD
