Metadata-Version: 2.1
Name: fastimgconcat
Version: 0.10
Summary: Concatenates a list of pictures (numpy arrays) without allocating new memory
Home-page: https://github.com/hansalemaos/fastimgconcat
Author: Johannes Fischer
Author-email: aulasparticularesdealemaosp@gmail.com
License: MIT
Keywords: concatenate,numpy
Classifier: Development Status :: 4 - Beta
Classifier: Programming Language :: Python :: 3 :: Only
Classifier: Programming Language :: Python :: 3.10
Classifier: Topic :: Software Development :: Libraries :: Python Modules
Classifier: Topic :: Utilities
License-File: LICENSE.rst
Requires-Dist: numpy
